xrpld_netgen/__init__.py
xrpld_netgen/cideploy/deploy.xahau.dockerfile
xrpld_netgen/cideploy/validators.txt
xrpld_netgen/cli.py
xrpld_netgen/default.xahau.features.json
xrpld_netgen/default.xrpl.features.json
xrpld_netgen/deploykit/ansible/clean.sh
xrpld_netgen/deploykit/ansible/clean.yml
xrpld_netgen/deploykit/ansible/deps.yml
xrpld_netgen/deploykit/ansible/main.yml
xrpld_netgen/deploykit/ansible/run.sh
xrpld_netgen/deploykit/config.json
xrpld_netgen/deploykit/network.entrypoint
xrpld_netgen/deploykit/nginx.dockerfile
xrpld_netgen/deploykit/prerequisites.sh
xrpld_netgen/deploykit/xahau.entrypoint
xrpld_netgen/deploykit/xrpl.entrypoint
xrpld_netgen/genesis.xahau.json
xrpld_netgen/genesis.xrpl.json
xrpld_netgen/libs/github.py
xrpld_netgen/libs/rippled.py
xrpld_netgen/main.py
xrpld_netgen/network.py
xrpld_netgen/rippled_cfg.py
xrpld_netgen/utils/deploy_kit.py
xrpld_netgen/utils/misc.py
xrpld_netgen-1.26.0.dist-info/METADATA
xrpld_netgen-1.26.0.dist-info/WHEEL
xrpld_netgen-1.26.0.dist-info/entry_points.txt
xrpld_netgen-1.26.0.dist-info/RECORD
