Metadata-Version: 2.3
Name: xrpld-netgen
Version: 1.26.0
Summary: Xrpld network generator
Author: Denis Angell
Author-email: dangell@transia.co
Requires-Python: >=3.9.6,<4.0.0
Classifier: Programming Language :: Python :: 3
Classifier: Programming Language :: Python :: 3.10
Classifier: Programming Language :: Python :: 3.11
Classifier: Programming Language :: Python :: 3.12
Classifier: Programming Language :: Python :: 3.13
Requires-Dist: pyyaml (>=6.0.1,<7.0.0)
Requires-Dist: requests (>=2.31.0,<3.0.0)
Requires-Dist: xrpld-publisher (>=2.0.0,<3.0.0)
